ultibi-0.7.0.dist-info/METADATA
ultibi-0.7.0.dist-info/WHEEL
ultibi-0.7.0.dist-info/license_files/LICENSE
ultibi/__init__.py
ultibi/internals/measure.py
ultibi/internals/db.py
ultibi/internals/__init__.py
ultibi/internals/datasource.py
ultibi/internals/dataset.py
ultibi/internals/requests.py
ultibi/internals/filters.py
ultibi/rust_module/__init__.py
ultibi/rust_module/ultibi_engine.abi3.so
ultibi-0.7.0.dist-info/RECORD
